music_duration/__init__.py
music_duration/duration.py
tests/__init__.py
tests/tests.py
music_duration-0.1.0.dist-info/METADATA
music_duration-0.1.0.dist-info/WHEEL
music_duration-0.1.0.dist-info/top_level.txt
music_duration-0.1.0.dist-info/RECORD
