Metadata-Version: 2.1
Name: music_duration
Version: 0.1.0
Summary: A library to find the duration of a music file
Home-page: https://github.com/yourusername/music_duration
Author: Your Name
Author-email: your.email@example.com
Classifier: Programming Language :: Python :: 3
Classifier: License :: OSI Approved :: MIT License
Classifier: Operating System :: OS Independent
Requires-Python: >=3.6
Requires-Dist: soundfile
